{"ShopData":{"CurrentKnifeIndex":0,"OpenedKnives":[0,0,1,42,18,2]},"PlayerData":{"Money":2149,"SlowMode":1,"LevelPass":1,"SecondLife":0,"Experience":155},"ProgressData":{"CurrentGamemod":0,"CurrentMarkLevel":2,"CurrentCubeLevel":0,"CurrentFlatLevel":0,"CurrentKnifeFestLevel":4,"CurrentStackKnifeLevel":0},"SettingsData":{"SoundVolume":0.0,"MusicVolume":0.0},"DailyGiftsData":{"_clock":{"Hours":7,"Minutes":53,"Seconds":5},"Date":"2021-10-30 07:55:03Z","UnlockedGifts":5,"PickedGifts":5},"_lotteryClock":{"Hours":0,"Minutes":0,"Seconds":0},"IsLotteryEnable":true,"CurrentGamemod":0,"CanShowStartAd":false}